piece/__auxiliary__.py
piece/__init__.py
piece/piecebase.py
piece/piecedataprogress.py
piece/piecedefine.py
piece/piecedesign.py
piece/pieceevaluate.py
piece/piecemain.py
piece/piecentry.py
piece/static/muscle5.1.linux_intel64
piece/static/muscle5.1.win64.exe
PMPrimer-1.0.7.dist-info/LICENSE
PMPrimer-1.0.7.dist-info/METADATA
PMPrimer-1.0.7.dist-info/WHEEL
PMPrimer-1.0.7.dist-info/entry_points.txt
PMPrimer-1.0.7.dist-info/top_level.txt
PMPrimer-1.0.7.dist-info/RECORD
