Metadata-Version: 2.1
Name: PMPrimer
Version: 1.0.7
Summary: automated design of multiplex PCR primer pairs for diverse templates
Home-page: https://github.com/AGIScuipeng/PMPrimer
Author: Nerium
License: MIT
Classifier: Programming Language :: Python :: 3
Classifier: License :: OSI Approved :: MIT License
Classifier: Environment :: Console
Classifier: Operating System :: Microsoft :: Windows
Classifier: Operating System :: POSIX :: Linux
License-File: LICENSE
Requires-Dist: primer3-py
Requires-Dist: seaborn
Requires-Dist: pandas
Requires-Dist: matplotlib
Requires-Dist: biopython
